Metadata-Version: 2.1
Name: StarPlus
Version: 1.0
Summary: A Package that makes setting up different modules easy.
Home-page: https://github.com/user/reponame
Download-URL: https://github.com/user/reponame/archive/v_01.tar.gz
Author: MrCoolkid
Author-email: mrcoolkidyt@gmail.com
License: MIT
Keywords: ComputerVision,ScreenRecording,PoseDetection
Classifier: Development Status :: 3 - Alpha
Classifier: Intended Audience :: Developers
Classifier: Topic :: Software Development :: Build Tools
Classifier: License :: OSI Approved :: MIT License
Classifier: Programming Language :: Python :: 3
Classifier: Programming Language :: Python :: 3.8
Classifier: Programming Language :: Python :: 3.7
Classifier: Programming Language :: Python :: 3.10
License-File: LICENSE.txt
